{"type":"FeatureCollection","name":"点","features":[{"type":"Feature","properties":{"NAME":"呼玛县","QUHUADAIMA":"232721","Location":4,"Alignment":3},"geometry":{"type":"Point","coordinates":[126.78200949341586,51.854219247522529]}},{"type":"Feature","properties":{"NAME":"漠河市","QUHUADAIMA":"232701","Location":6,"Alignment":1},"geometry":{"type":"Point","coordinates":[122.65682770607037,53.099929291151547]}},{"type":"Feature","properties":{"NAME":"塔河县","QUHUADAIMA":"232722","Location":6,"Alignment":1},"geometry":{"type":"Point","coordinates":[124.83257405253417,52.464158208252847]}}]}