{"type":"FeatureCollection","name":"点","features":[{"type":"Feature","properties":{"NAME":"东至县","QUHUADAIMA":"341721","Location":6,"Alignment":1},"geometry":{"type":"Point","coordinates":[117.14429455834177,30.231818462242668]}},{"type":"Feature","properties":{"NAME":"石台县","QUHUADAIMA":"341722","Location":6,"Alignment":1},"geometry":{"type":"Point","coordinates":[117.60841548863759,30.3420359901566]}},{"type":"Feature","properties":{"NAME":"青阳县","QUHUADAIMA":"341723","Location":6,"Alignment":1},"geometry":{"type":"Point","coordinates":[117.98193342973902,30.77443103568999]}},{"type":"Feature","properties":{"NAME":"贵池区","QUHUADAIMA":"341702","Location":6,"Alignment":1},"geometry":{"type":"Point","coordinates":[117.60529691310298,30.777472874653142]}}]}