{"type":"FeatureCollection","name":"点","features":[{"type":"Feature","properties":{"NAME":"乐平市","QUHUADAIMA":"360281","Location":6,"Alignment":1},"geometry":{"type":"Point","coordinates":[117.25371421844181,29.097677910458426]}},{"type":"Feature","properties":{"NAME":"浮梁县","QUHUADAIMA":"360222","Location":2,"Alignment":2},"geometry":{"type":"Point","coordinates":[117.33448691932124,29.484431281228197]}},{"type":"Feature","properties":{"NAME":"昌江区","QUHUADAIMA":"360202","Location":8,"Alignment":2},"geometry":{"type":"Point","coordinates":[117.31131361728724,29.410031077456619]}},{"type":"Feature","properties":{"NAME":"珠山区","QUHUADAIMA":"360203","Location":6,"Alignment":1},"geometry":{"type":"Point","coordinates":[117.33561221277125,29.432529418801931]}}]}