{"type":"FeatureCollection","name":"点","features":[{"type":"Feature","properties":{"NAME":"六枝特区","QUHUADAIMA":"520203","Location":7,"Alignment":3},"geometry":{"type":"Point","coordinates":[105.61051511620636,26.3386520366555]}},{"type":"Feature","properties":{"NAME":"钟山区","QUHUADAIMA":"520201","Location":2,"Alignment":2},"geometry":{"type":"Point","coordinates":[104.96647052277235,26.709713454504008]}},{"type":"Feature","properties":{"NAME":"水城县","QUHUADAIMA":"520221","Location":8,"Alignment":2},"geometry":{"type":"Point","coordinates":[105.0527482685752,26.694396012251264]}},{"type":"Feature","properties":{"NAME":"盘州市","QUHUADAIMA":"520281","Location":6,"Alignment":1},"geometry":{"type":"Point","coordinates":[104.61193897508838,25.846030750143914]}}]}