{"type":"FeatureCollection","name":"点","features":[{"type":"Feature","properties":{"NAME":"宜君县","QUHUADAIMA":"610222","Location":6,"Alignment":1},"geometry":{"type":"Point","coordinates":[109.23976636280699,35.52468434106332]}},{"type":"Feature","properties":{"NAME":"印台区","QUHUADAIMA":"610203","Location":6,"Alignment":1},"geometry":{"type":"Point","coordinates":[109.22093541172329,35.247958183120396]}},{"type":"Feature","properties":{"NAME":"王益区","QUHUADAIMA":"610202","Location":8,"Alignment":2},"geometry":{"type":"Point","coordinates":[109.22658360609717,35.205029062979264]}},{"type":"Feature","properties":{"NAME":"耀州区","QUHUADAIMA":"610204","Location":4,"Alignment":3},"geometry":{"type":"Point","coordinates":[109.1101498790205,35.040119743130646]}}]}