{"type":"FeatureCollection","name":"点","features":[{"type":"Feature","properties":{"NAME":"河南蒙古族自治县","QUHUADAIMA":"632324","Location":6,"Alignment":1},"geometry":{"type":"Point","coordinates":[101.74163771082108,34.864883001633622]}},{"type":"Feature","properties":{"NAME":"泽库县","QUHUADAIMA":"632323","Location":4,"Alignment":3},"geometry":{"type":"Point","coordinates":[101.59512889963311,35.165498298917271]}},{"type":"Feature","properties":{"NAME":"同仁县","QUHUADAIMA":"632321","Location":6,"Alignment":1},"geometry":{"type":"Point","coordinates":[102.14175532507508,35.644509773485353]}},{"type":"Feature","properties":{"NAME":"尖扎县","QUHUADAIMA":"632322","Location":4,"Alignment":3},"geometry":{"type":"Point","coordinates":[102.16048444450368,36.06971803589731]}}]}