{"type":"FeatureCollection","name":"点","features":[{"type":"Feature","properties":{"NAME":"独山子区","QUHUADAIMA":"650202","Location":6,"Alignment":1},"geometry":{"type":"Point","coordinates":[84.991796997032438,44.442566012780659]}},{"type":"Feature","properties":{"NAME":"克拉玛依区","QUHUADAIMA":"650203","Location":8,"Alignment":2},"geometry":{"type":"Point","coordinates":[84.990157769698513,45.715062785410041]}},{"type":"Feature","properties":{"NAME":"白碱滩区","QUHUADAIMA":"650204","Location":6,"Alignment":1},"geometry":{"type":"Point","coordinates":[85.2756383804462,45.824409992686647]}},{"type":"Feature","properties":{"NAME":"乌尔禾区","QUHUADAIMA":"650205","Location":6,"Alignment":1},"geometry":{"type":"Point","coordinates":[85.823170163708767,46.220626005118177]}}]}